django_hls/__init__.py
django_hls/apps.py
django_hls/conf.py
django_hls/models.py
django_hls/tasks.py
django_hls/tests.py
django_hls/utils.py
django_hls/migrations/0001_initial.py
django_hls/migrations/__init__.py
django_hls/services/__init__.py
django_hls/services/ffmpeg_runner.py
django_hls/services/hls_generator.py
django_hls/services/key_manager.py
django_hls-1.6.0.dist-info/licenses/LICENSE
django_hls-1.6.0.dist-info/METADATA
django_hls-1.6.0.dist-info/WHEEL
django_hls-1.6.0.dist-info/top_level.txt
django_hls-1.6.0.dist-info/RECORD
